youtube_stats-0.1.3.dist-info/METADATA
youtube_stats-0.1.3.dist-info/WHEEL
youtube_stats/__init__.py
youtube_stats/youtube_stats.cp312-win_amd64.pyd
youtube_stats-0.1.3.dist-info/RECORD
