Metadata-Version: 2.4
Name: youtube_stats
Version: 0.1.3
